usersgenerator
