Metadata-Version: 2.1
Name: usersgenerator
Version: 2.1.0
Summary: Generate possible users of an organization from some names
Home-page: https://github.com/abeljm/UsersGenerator
Author: Avelino Navarro
Author-email: abeljm2017@gmail.com
License: UNKNOWN
Platform: UNKNOWN
Classifier: Programming Language :: Python :: 3
Classifier: Programming Language :: Python :: 3.9
Classifier: License :: OSI Approved :: GNU General Public License v3 (GPLv3)
